mloyalty/__init__.py
mloyalty/base.py
mloyalty/campaign.py
mloyalty/cheque.py
mloyalty/client.py
mloyalty/operator.py
mloyalty/pos.py
mloyalty/db/__init__.py
mloyalty/db/backends/__init__.py
mloyalty/db/backends/tinydb.py
mloyalty/utils/__init__.py
mloyalty/utils/module_loading.py
tests/__init__.py
tests/test_campaign.py
tests/test_cheque.py
tests/test_client.py
tests/test_mloyalty.py
tests/test_operator.py
tests/test_pos.py
mloyalty-0.2.4.dist-info/LICENSE
mloyalty-0.2.4.dist-info/METADATA
mloyalty-0.2.4.dist-info/WHEEL
mloyalty-0.2.4.dist-info/top_level.txt
mloyalty-0.2.4.dist-info/RECORD
