Metadata-Version: 2.1
Name: mloyalty
Version: 0.2.4
Summary: Python API for Mloyalty
Home-page: https://github.com/igorexa256/mloyalty
Author: Igor Belyansky
Author-email: igorexa256@gmail.com
License: MIT
Keywords: python mloyalty api wrapper
Platform: UNKNOWN
Classifier: License :: OSI Approved :: MIT License
Classifier: Operating System :: OS Independent
Classifier: Programming Language :: Python :: 3
Requires-Dist: requests
Requires-Dist: pyjwt
Requires-Dist: tinydb
Requires-Dist: python-dotenv
